{
  "date": "2026-02-04",
  "ranking": "新高値",
  "count": 44,
  "items": [
    {
      "rank": 1,
      "code": "7771",
      "name": "日本精密",
      "market": "スタンダード",
      "sector": "精密機器",
      "industry": "電機・精密",
      "tags": [
        "tse",
        "standard",
        "精密機器",
        "電機・精密"
      ],
      "close": 415.0,
      "change": 80.0,
      "changePercent": 23.8806,
      "volume": 5584600,
      "volumeRatio25": 0.9354,
      "distanceToMa25": 71.7431,
      "distanceToMa75": 198.9339,
      "distanceToMa200": 286.73,
      "rci12": 46.85,
      "rci24": 82.11,
      "rci48": 85.97,
      "rangePosition52w": 100.0,
      "newHigh52w": true,
      "links": {
        "quote": "https://finance.yahoo.co.jp/quote/7771.T"
      }
    },
    {
      "rank": 2,
      "code": "8920",
      "name": "東祥",
      "market": "スタンダード",
      "sector": "サービス業",
      "industry": "情報通信・サービスその他",
      "tags": [
        "tse",
        "standard",
        "サービス業",
        "情報通信・サービスその他"
      ],
      "close": 906.0,
      "change": 150.0,
      "changePercent": 19.8413,
      "volume": 710100,
      "volumeRatio25": 5.6832,
      "distanceToMa25": 16.7706,
      "distanceToMa75": 16.1817,
      "distanceToMa200": 29.5831,
      "rci12": -30.77,
      "rci24": -49.15,
      "rci48": -29.1,
      "rangePosition52w": 100.0,
      "newHigh52w": true,
      "links": {
        "quote": "https://finance.yahoo.co.jp/quote/8920.T"
      }
    },
    {
      "rank": 3,
      "code": "7922",
      "name": "三光産業",
      "market": "スタンダード",
      "sector": "その他製品",
      "industry": "情報通信・サービスその他",
      "tags": [
        "tse",
        "standard",
        "その他製品",
        "情報通信・サービスその他"
      ],
      "close": 513.0,
      "change": 80.0,
      "changePercent": 18.4758,
      "volume": 7500,
      "volumeRatio25": 1.2652,
      "distanceToMa25": 15.136,
      "distanceToMa75": 19.7069,
      "distanceToMa200": 24.5902,
      "rci12": -41.78,
      "rci24": 17.91,
      "rci48": 62.17,
      "rangePosition52w": 100.0,
      "newHigh52w": true,
      "links": {
        "quote": "https://finance.yahoo.co.jp/quote/7922.T"
      }
    },
    {
      "rank": 4,
      "code": "1515",
      "name": "日鉄鉱業",
      "market": "プライム",
      "sector": "鉱業",
      "industry": "エネルギー資源",
      "tags": [
        "tse",
        "prime",
        "鉱業",
        "エネルギー資源"
      ],
      "close": 3975.0,
      "change": 415.0,
      "changePercent": 11.6573,
      "volume": 2028000,
      "volumeRatio25": 1.2674,
      "distanceToMa25": 32.0054,
      "distanceToMa75": 78.6442,
      "distanceToMa200": 123.0621,
      "rci12": 83.22,
      "rci24": 94.96,
      "rci48": 98.37,
      "rangePosition52w": 100.0,
      "newHigh52w": true,
      "links": {
        "quote": "https://finance.yahoo.co.jp/quote/1515.T"
      }
    },
    {
      "rank": 5,
      "code": "3315",
      "name": "日本コークス工業",
      "market": "プライム",
      "sector": "石油・石炭製品",
      "industry": "エネルギー資源",
      "tags": [
        "tse",
        "prime",
        "石油・石炭製品",
        "エネルギー資源"
      ],
      "close": 125.0,
      "change": 10.0,
      "changePercent": 8.6957,
      "volume": 7807600,
      "volumeRatio25": 2.2286,
      "distanceToMa25": 12.7752,
      "distanceToMa75": 20.843,
      "distanceToMa200": 31.3991,
      "rci12": 73.43,
      "rci24": -23.15,
      "rci48": 35.27,
      "rangePosition52w": 100.0,
      "newHigh52w": true,
      "links": {
        "quote": "https://finance.yahoo.co.jp/quote/3315.T"
      }
    },
    {
      "rank": 6,
      "code": "6741",
      "name": "日本信号",
      "market": "プライム",
      "sector": "電気機器",
      "industry": "電機・精密",
      "tags": [
        "tse",
        "prime",
        "電気機器",
        "電機・精密"
      ],
      "close": 1611.0,
      "change": 127.0,
      "changePercent": 8.558,
      "volume": 903100,
      "volumeRatio25": 4.7992,
      "distanceToMa25": 18.3584,
      "distanceToMa75": 24.854,
      "distanceToMa200": 37.4609,
      "rci12": -9.09,
      "rci24": 40.48,
      "rci48": 82.53,
      "rangePosition52w": 100.0,
      "newHigh52w": true,
      "links": {
        "quote": "https://finance.yahoo.co.jp/quote/6741.T"
      }
    },
    {
      "rank": 7,
      "code": "8365",
      "name": "富山銀行",
      "market": "スタンダード",
      "sector": "銀行業",
      "industry": "銀行",
      "tags": [
        "tse",
        "standard",
        "銀行業",
        "銀行"
      ],
      "close": 2447.0,
      "change": 181.0,
      "changePercent": 7.9876,
      "volume": 27600,
      "volumeRatio25": 2.1489,
      "distanceToMa25": 15.4267,
      "distanceToMa75": 29.8253,
      "distanceToMa200": 44.0674,
      "rci12": 24.48,
      "rci24": 79.13,
      "rci48": 93.89,
      "rangePosition52w": 100.0,
      "newHigh52w": true,
      "links": {
        "quote": "https://finance.yahoo.co.jp/quote/8365.T"
      }
    },
    {
      "rank": 8,
      "code": "6503",
      "name": "三菱電機",
      "market": "プライム",
      "sector": "電気機器",
      "industry": "電機・精密",
      "tags": [
        "tse",
        "prime",
        "電気機器",
        "電機・精密"
      ],
      "close": 5383.0,
      "change": 383.0,
      "changePercent": 7.66,
      "volume": 14837800,
      "volumeRatio25": 2.6527,
      "distanceToMa25": 9.8437,
      "distanceToMa75": 19.434,
      "distanceToMa200": 44.7686,
      "rci12": -6.29,
      "rci24": 38.41,
      "rci48": 85.69,
      "rangePosition52w": 100.0,
      "newHigh52w": true,
      "links": {
        "quote": "https://finance.yahoo.co.jp/quote/6503.T"
      }
    },
    {
      "rank": 9,
      "code": "6743",
      "name": "大同信号",
      "market": "スタンダード",
      "sector": "電気機器",
      "industry": "電機・精密",
      "tags": [
        "tse",
        "standard",
        "電気機器",
        "電機・精密"
      ],
      "close": 903.0,
      "change": 64.0,
      "changePercent": 7.6281,
      "volume": 107100,
      "volumeRatio25": 3.1917,
      "distanceToMa25": 10.4398,
      "distanceToMa75": 22.6547,
      "distanceToMa200": 48.7595,
      "rci12": 31.64,
      "rci24": -27.63,
      "rci48": 73.08,
      "rangePosition52w": 100.0,
      "newHigh52w": true,
      "links": {
        "quote": "https://finance.yahoo.co.jp/quote/6743.T"
      }
    },
    {
      "rank": 10,
      "code": "6305",
      "name": "日立建機",
      "market": "プライム",
      "sector": "機械",
      "industry": "機械",
      "tags": [
        "tse",
        "prime",
        "機械"
      ],
      "close": 5976.0,
      "change": 420.0,
      "changePercent": 7.5594,
      "volume": 2355100,
      "volumeRatio25": 2.3554,
      "distanceToMa25": 17.1039,
      "distanceToMa75": 24.107,
      "distanceToMa200": 30.1793,
      "rci12": 23.08,
      "rci24": 60.26,
      "rci48": 86.3,
      "rangePosition52w": 100.0,
      "newHigh52w": true,
      "links": {
        "quote": "https://finance.yahoo.co.jp/quote/6305.T"
      }
    },
    {
      "rank": 11,
      "code": "8562",
      "name": "福島銀行",
      "market": "スタンダード",
      "sector": "銀行業",
      "industry": "銀行",
      "tags": [
        "tse",
        "standard",
        "銀行業",
        "銀行"
      ],
      "close": 352.0,
      "change": 24.0,
      "changePercent": 7.3171,
      "volume": 810600,
      "volumeRatio25": 2.1933,
      "distanceToMa25": 13.7098,
      "distanceToMa75": 33.4209,
      "distanceToMa200": 46.1824,
      "rci12": 21.85,
      "rci24": 74.43,
      "rci48": 94.49,
      "rangePosition52w": 100.0,
      "newHigh52w": true,
      "links": {
        "quote": "https://finance.yahoo.co.jp/quote/8562.T"
      }
    },
    {
      "rank": 12,
      "code": "6343",
      "name": "フリージア・マクロス",
      "market": "スタンダード",
      "sector": "機械",
      "industry": "機械",
      "tags": [
        "tse",
        "standard",
        "機械"
      ],
      "close": 192.0,
      "change": 9.0,
      "changePercent": 4.918,
      "volume": 676400,
      "volumeRatio25": 1.828,
      "distanceToMa25": 10.016,
      "distanceToMa75": 23.5203,
      "distanceToMa200": 49.4571,
      "rci12": 51.75,
      "rci24": 86.04,
      "rci48": 96.94,
      "rangePosition52w": 100.0,
      "newHigh52w": true,
      "links": {
        "quote": "https://finance.yahoo.co.jp/quote/6343.T"
      }
    },
    {
      "rank": 13,
      "code": "6165",
      "name": "パンチ工業",
      "market": "スタンダード",
      "sector": "機械",
      "industry": "機械",
      "tags": [
        "tse",
        "standard",
        "機械"
      ],
      "close": 525.0,
      "change": 24.0,
      "changePercent": 4.7904,
      "volume": 211800,
      "volumeRatio25": 3.0648,
      "distanceToMa25": 5.7871,
      "distanceToMa75": 14.1668,
      "distanceToMa200": 24.7475,
      "rci12": 18.01,
      "rci24": 18.85,
      "rci48": 68.14,
      "rangePosition52w": 100.0,
      "newHigh52w": true,
      "links": {
        "quote": "https://finance.yahoo.co.jp/quote/6165.T"
      }
    },
    {
      "rank": 14,
      "code": "8331",
      "name": "千葉銀行",
      "market": "プライム",
      "sector": "銀行業",
      "industry": "銀行",
      "tags": [
        "tse",
        "prime",
        "銀行業",
        "銀行"
      ],
      "close": 2276.5,
      "change": 101.5,
      "changePercent": 4.6667,
      "volume": 4071700,
      "volumeRatio25": 1.5598,
      "distanceToMa25": 15.0817,
      "distanceToMa75": 32.2824,
      "distanceToMa200": 51.0006,
      "rci12": 88.11,
      "rci24": 86.96,
      "rci48": 97.7,
      "rangePosition52w": 100.0,
      "newHigh52w": true,
      "links": {
        "quote": "https://finance.yahoo.co.jp/quote/8331.T"
      }
    },
    {
      "rank": 15,
      "code": "7713",
      "name": "シグマ光機",
      "market": "スタンダード",
      "sector": "精密機器",
      "industry": "電機・精密",
      "tags": [
        "tse",
        "standard",
        "精密機器",
        "電機・精密"
      ],
      "close": 1706.0,
      "change": 73.0,
      "changePercent": 4.4703,
      "volume": 28200,
      "volumeRatio25": 1.8805,
      "distanceToMa25": 8.0184,
      "distanceToMa75": 11.4052,
      "distanceToMa200": 18.1265,
      "rci12": 25.7,
      "rci24": 62.17,
      "rci48": 83.24,
      "rangePosition52w": 100.0,
      "newHigh52w": true,
      "links": {
        "quote": "https://finance.yahoo.co.jp/quote/7713.T"
      }
    },
    {
      "rank": 16,
      "code": "8308",
      "name": "りそなホールディングス",
      "market": "プライム",
      "sector": "銀行業",
      "industry": "銀行",
      "tags": [
        "tse",
        "prime",
        "銀行業",
        "銀行"
      ],
      "close": 1929.0,
      "change": 78.5,
      "changePercent": 4.2421,
      "volume": 12507100,
      "volumeRatio25": 1.2912,
      "distanceToMa25": 12.7859,
      "distanceToMa75": 21.5292,
      "distanceToMa200": 34.8491,
      "rci12": 44.76,
      "rci24": 78.43,
      "rci48": 65.88,
      "rangePosition52w": 100.0,
      "newHigh52w": true,
      "links": {
        "quote": "https://finance.yahoo.co.jp/quote/8308.T"
      }
    },
    {
      "rank": 17,
      "code": "7670",
      "name": "オーウエル",
      "market": "スタンダード",
      "sector": "卸売業",
      "industry": "商社・卸売",
      "tags": [
        "tse",
        "standard",
        "卸売業",
        "商社・卸売"
      ],
      "close": 1211.0,
      "change": 49.0,
      "changePercent": 4.2169,
      "volume": 11000,
      "volumeRatio25": 1.3215,
      "distanceToMa25": 10.7879,
      "distanceToMa75": 17.0154,
      "distanceToMa200": 24.6148,
      "rci12": 94.23,
      "rci24": 86.8,
      "rci48": 90.38,
      "rangePosition52w": 100.0,
      "newHigh52w": true,
      "links": {
        "quote": "https://finance.yahoo.co.jp/quote/7670.T"
      }
    },
    {
      "rank": 18,
      "code": "7409",
      "name": "ＡｅｒｏＥｄｇｅ",
      "market": "グロース",
      "sector": "輸送用機器",
      "industry": "自動車・輸送機",
      "tags": [
        "tse",
        "growth",
        "輸送用機器",
        "自動車・輸送機"
      ],
      "close": 3760.0,
      "change": 150.0,
      "changePercent": 4.1551,
      "volume": 147100,
      "volumeRatio25": 0.5522,
      "distanceToMa25": 23.7787,
      "distanceToMa75": 58.5558,
      "distanceToMa200": 137.045,
      "rci12": 85.31,
      "rci24": 97.04,
      "rci48": 75.95,
      "rangePosition52w": 100.0,
      "newHigh52w": true,
      "links": {
        "quote": "https://finance.yahoo.co.jp/quote/7409.T"
      }
    },
    {
      "rank": 19,
      "code": "6785",
      "name": "鈴木",
      "market": "プライム",
      "sector": "電気機器",
      "industry": "電機・精密",
      "tags": [
        "tse",
        "prime",
        "電気機器",
        "電機・精密"
      ],
      "close": 2665.0,
      "change": 96.0,
      "changePercent": 3.7369,
      "volume": 129200,
      "volumeRatio25": 1.6548,
      "distanceToMa25": 9.2249,
      "distanceToMa75": 14.9506,
      "distanceToMa200": 31.1726,
      "rci12": 72.9,
      "rci24": 53.33,
      "rci48": 77.7,
      "rangePosition52w": 100.0,
      "newHigh52w": true,
      "links": {
        "quote": "https://finance.yahoo.co.jp/quote/6785.T"
      }
    },
    {
      "rank": 20,
      "code": "6835",
      "name": "アライドテレシスホールディングス",
      "market": "スタンダード",
      "sector": "電気機器",
      "industry": "電機・精密",
      "tags": [
        "tse",
        "standard",
        "電気機器",
        "電機・精密"
      ],
      "close": 342.0,
      "change": 12.0,
      "changePercent": 3.6364,
      "volume": 736800,
      "volumeRatio25": 1.1629,
      "distanceToMa25": 15.5405,
      "distanceToMa75": 37.1658,
      "distanceToMa200": 68.0136,
      "rci12": 92.31,
      "rci24": 94.57,
      "rci48": 97.67,
      "rangePosition52w": 100.0,
      "newHigh52w": true,
      "links": {
        "quote": "https://finance.yahoo.co.jp/quote/6835.T"
      }
    },
    {
      "rank": 21,
      "code": "8354",
      "name": "ふくおかフィナンシャルグループ",
      "market": "プライム",
      "sector": "銀行業",
      "industry": "銀行",
      "tags": [
        "tse",
        "prime",
        "銀行業",
        "銀行"
      ],
      "close": 6054.0,
      "change": 198.0,
      "changePercent": 3.3811,
      "volume": 1259700,
      "volumeRatio25": 1.5573,
      "distanceToMa25": 10.5883,
      "distanceToMa75": 22.6681,
      "distanceToMa200": 37.6923,
      "rci12": 51.75,
      "rci24": 74.78,
      "rci48": 95.18,
      "rangePosition52w": 100.0,
      "newHigh52w": true,
      "links": {
        "quote": "https://finance.yahoo.co.jp/quote/8354.T"
      }
    },
    {
      "rank": 22,
      "code": "8359",
      "name": "八十二長野銀行",
      "market": "プライム",
      "sector": "銀行業",
      "industry": "銀行",
      "tags": [
        "tse",
        "prime",
        "銀行業",
        "銀行"
      ],
      "close": 2057.5,
      "change": 66.5,
      "changePercent": 3.34,
      "volume": 1507600,
      "volumeRatio25": 1.3469,
      "distanceToMa25": 10.6766,
      "distanceToMa75": 22.3586,
      "distanceToMa200": 44.4796,
      "rci12": 57.87,
      "rci24": 82.85,
      "rci48": 88.3,
      "rangePosition52w": 100.0,
      "newHigh52w": true,
      "links": {
        "quote": "https://finance.yahoo.co.jp/quote/8359.T"
      }
    },
    {
      "rank": 23,
      "code": "8364",
      "name": "清水銀行",
      "market": "プライム",
      "sector": "銀行業",
      "industry": "銀行",
      "tags": [
        "tse",
        "prime",
        "銀行業",
        "銀行"
      ],
      "close": 2606.0,
      "change": 84.0,
      "changePercent": 3.3307,
      "volume": 30900,
      "volumeRatio25": 0.8138,
      "distanceToMa25": 4.6469,
      "distanceToMa75": 16.2272,
      "distanceToMa200": 41.7653,
      "rci12": 48.25,
      "rci24": 41.59,
      "rci48": 88.34,
      "rangePosition52w": 100.0,
      "newHigh52w": true,
      "links": {
        "quote": "https://finance.yahoo.co.jp/quote/8364.T"
      }
    },
    {
      "rank": 24,
      "code": "2607",
      "name": "不二製油",
      "market": "プライム",
      "sector": "食料品",
      "industry": "食品",
      "tags": [
        "tse",
        "prime",
        "食料品",
        "食品"
      ],
      "close": 4229.0,
      "change": 136.0,
      "changePercent": 3.3227,
      "volume": 272400,
      "volumeRatio25": 0.9908,
      "distanceToMa25": 7.3481,
      "distanceToMa75": 17.8734,
      "distanceToMa200": 27.8068,
      "rci12": 6.47,
      "rci24": 86.11,
      "rci48": 91.59,
      "rangePosition52w": 100.0,
      "newHigh52w": true,
      "links": {
        "quote": "https://finance.yahoo.co.jp/quote/2607.T"
      }
    },
    {
      "rank": 25,
      "code": "1867",
      "name": "植木組",
      "market": "スタンダード",
      "sector": "建設業",
      "industry": "建設・資材",
      "tags": [
        "tse",
        "standard",
        "建設業",
        "建設・資材"
      ],
      "close": 3085.0,
      "change": 90.0,
      "changePercent": 3.005,
      "volume": 18800,
      "volumeRatio25": 2.6934,
      "distanceToMa25": 7.6203,
      "distanceToMa75": 14.9541,
      "distanceToMa200": 31.8796,
      "rci12": 67.83,
      "rci24": 50.87,
      "rci48": 82.31,
      "rangePosition52w": 100.0,
      "newHigh52w": true,
      "links": {
        "quote": "https://finance.yahoo.co.jp/quote/1867.T"
      }
    },
    {
      "rank": 26,
      "code": "7186",
      "name": "横浜フィナンシャルグループ",
      "market": "プライム",
      "sector": "銀行業",
      "industry": "銀行",
      "tags": [
        "tse",
        "prime",
        "銀行業",
        "銀行"
      ],
      "close": 1491.5,
      "change": 43.0,
      "changePercent": 2.9686,
      "volume": 4215300,
      "volumeRatio25": 1.4114,
      "distanceToMa25": 8.0703,
      "distanceToMa75": 18.7279,
      "distanceToMa200": 36.2418,
      "rci12": 31.47,
      "rci24": 65.76,
      "rci48": 93.54,
      "rangePosition52w": 100.0,
      "newHigh52w": true,
      "links": {
        "quote": "https://finance.yahoo.co.jp/quote/7186.T"
      }
    },
    {
      "rank": 27,
      "code": "2208",
      "name": "ブルボン",
      "market": "スタンダード",
      "sector": "食料品",
      "industry": "食品",
      "tags": [
        "tse",
        "standard",
        "食料品",
        "食品"
      ],
      "close": 2940.0,
      "change": 75.0,
      "changePercent": 2.6178,
      "volume": 17500,
      "volumeRatio25": 0.9916,
      "distanceToMa25": 8.7664,
      "distanceToMa75": 16.2068,
      "distanceToMa200": 14.7803,
      "rci12": 48.25,
      "rci24": 88.28,
      "rci48": 96.8,
      "rangePosition52w": 100.0,
      "newHigh52w": true,
      "links": {
        "quote": "https://finance.yahoo.co.jp/quote/2208.T"
      }
    },
    {
      "rank": 28,
      "code": "4008",
      "name": "住友精化",
      "market": "プライム",
      "sector": "化学",
      "industry": "素材・化学",
      "tags": [
        "tse",
        "prime",
        "化学",
        "素材・化学"
      ],
      "close": 5490.0,
      "change": 130.0,
      "changePercent": 2.4254,
      "volume": 31600,
      "volumeRatio25": 0.981,
      "distanceToMa25": 2.0826,
      "distanceToMa75": 5.7097,
      "distanceToMa200": 14.5821,
      "rci12": -5.42,
      "rci24": -16.48,
      "rci48": 54.13,
      "rangePosition52w": 100.0,
      "newHigh52w": true,
      "links": {
        "quote": "https://finance.yahoo.co.jp/quote/4008.T"
      }
    },
    {
      "rank": 29,
      "code": "5304",
      "name": "ＳＥＣカーボン",
      "market": "スタンダード",
      "sector": "ガラス・土石製品",
      "industry": "建設・資材",
      "tags": [
        "tse",
        "standard",
        "ガラス・土石製品",
        "建設・資材"
      ],
      "close": 2849.0,
      "change": 66.0,
      "changePercent": 2.3715,
      "volume": 115200,
      "volumeRatio25": 2.2801,
      "distanceToMa25": 7.1488,
      "distanceToMa75": 20.6202,
      "distanceToMa200": 30.3309,
      "rci12": -18.18,
      "rci24": 50.72,
      "rci48": 88.18,
      "rangePosition52w": 100.0,
      "newHigh52w": true,
      "links": {
        "quote": "https://finance.yahoo.co.jp/quote/5304.T"
      }
    },
    {
      "rank": 30,
      "code": "3109",
      "name": "シキボウ",
      "market": "プライム",
      "sector": "繊維製品",
      "industry": "素材・化学",
      "tags": [
        "tse",
        "prime",
        "繊維製品",
        "素材・化学"
      ],
      "close": 1103.0,
      "change": 25.0,
      "changePercent": 2.3191,
      "volume": 67800,
      "volumeRatio25": 1.2568,
      "distanceToMa25": 2.7155,
      "distanceToMa75": 6.3932,
      "distanceToMa200": 9.5931,
      "rci12": 2.8,
      "rci24": 26.43,
      "rci48": 81.42,
      "rangePosition52w": 100.0,
      "newHigh52w": true,
      "links": {
        "quote": "https://finance.yahoo.co.jp/quote/3109.T"
      }
    },
    {
      "rank": 31,
      "code": "8399",
      "name": "琉球銀行",
      "market": "プライム",
      "sector": "銀行業",
      "industry": "銀行",
      "tags": [
        "tse",
        "prime",
        "銀行業",
        "銀行"
      ],
      "close": 2327.0,
      "change": 51.0,
      "changePercent": 2.2408,
      "volume": 135600,
      "volumeRatio25": 0.9163,
      "distanceToMa25": 11.6024,
      "distanceToMa75": 30.0591,
      "distanceToMa200": 62.3889,
      "rci12": 51.57,
      "rci24": 91.11,
      "rci48": 93.8,
      "rangePosition52w": 100.0,
      "newHigh52w": true,
      "links": {
        "quote": "https://finance.yahoo.co.jp/quote/8399.T"
      }
    },
    {
      "rank": 32,
      "code": "4972",
      "name": "綜研化学",
      "market": "スタンダード",
      "sector": "化学",
      "industry": "素材・化学",
      "tags": [
        "tse",
        "standard",
        "化学",
        "素材・化学"
      ],
      "close": 2944.0,
      "change": 61.0,
      "changePercent": 2.1159,
      "volume": 86000,
      "volumeRatio25": 1.5413,
      "distanceToMa25": 7.3277,
      "distanceToMa75": 15.4437,
      "distanceToMa200": 48.4619,
      "rci12": 94.41,
      "rci24": 93.24,
      "rci48": 89.57,
      "rangePosition52w": 100.0,
      "newHigh52w": true,
      "links": {
        "quote": "https://finance.yahoo.co.jp/quote/4972.T"
      }
    },
    {
      "rank": 33,
      "code": "8830",
      "name": "住友不動産",
      "market": "プライム",
      "sector": "不動産業",
      "industry": "不動産",
      "tags": [
        "tse",
        "prime",
        "不動産業",
        "不動産"
      ],
      "close": 4506.0,
      "change": 86.0,
      "changePercent": 1.9457,
      "volume": 2080000,
      "volumeRatio25": 0.827,
      "distanceToMa25": 8.0203,
      "distanceToMa75": 18.6268,
      "distanceToMa200": 38.9237,
      "rci12": 95.8,
      "rci24": 74.0,
      "rci48": 92.64,
      "rangePosition52w": 100.0,
      "newHigh52w": true,
      "links": {
        "quote": "https://finance.yahoo.co.jp/quote/8830.T"
      }
    },
    {
      "rank": 34,
      "code": "3501",
      "name": "ＳＵＭＩＮＯＥ",
      "market": "プライム",
      "sector": "繊維製品",
      "industry": "素材・化学",
      "tags": [
        "tse",
        "prime",
        "繊維製品",
        "素材・化学"
      ],
      "close": 1315.0,
      "change": 23.0,
      "changePercent": 1.7802,
      "volume": 29800,
      "volumeRatio25": 1.1672,
      "distanceToMa25": 2.863,
      "distanceToMa75": 6.2128,
      "distanceToMa200": 10.0603,
      "rci12": 2.45,
      "rci24": 45.26,
      "rci48": 77.46,
      "rangePosition52w": 100.0,
      "newHigh52w": true,
      "links": {
        "quote": "https://finance.yahoo.co.jp/quote/3501.T"
      }
    },
    {
      "rank": 35,
      "code": "9265",
      "name": "ヤマシタヘルスケアホールディングス",
      "market": "スタンダード",
      "sector": "卸売業",
      "industry": "商社・卸売",
      "tags": [
        "tse",
        "standard",
        "卸売業",
        "商社・卸売"
      ],
      "close": 3735.0,
      "change": 60.0,
      "changePercent": 1.6327,
      "volume": 500,
      "volumeRatio25": 0.7862,
      "distanceToMa25": 12.0612,
      "distanceToMa75": 14.7207,
      "distanceToMa200": 23.4439,
      "rci12": 81.82,
      "rci24": 73.57,
      "rci48": 70.66,
      "rangePosition52w": 100.0,
      "newHigh52w": true,
      "links": {
        "quote": "https://finance.yahoo.co.jp/quote/9265.T"
      }
    },
    {
      "rank": 36,
      "code": "3004",
      "name": "神栄",
      "market": "スタンダード",
      "sector": "卸売業",
      "industry": "商社・卸売",
      "tags": [
        "tse",
        "standard",
        "卸売業",
        "商社・卸売"
      ],
      "close": 2688.0,
      "change": 42.0,
      "changePercent": 1.5873,
      "volume": 6800,
      "volumeRatio25": 0.7265,
      "distanceToMa25": 7.5114,
      "distanceToMa75": 14.0897,
      "distanceToMa200": 29.2103,
      "rci12": 38.46,
      "rci24": 60.26,
      "rci48": 88.48,
      "rangePosition52w": 100.0,
      "newHigh52w": true,
      "links": {
        "quote": "https://finance.yahoo.co.jp/quote/3004.T"
      }
    },
    {
      "rank": 37,
      "code": "9001",
      "name": "東武鉄道",
      "market": "プライム",
      "sector": "陸運業",
      "industry": "運輸・物流",
      "tags": [
        "tse",
        "prime",
        "陸運業",
        "運輸・物流"
      ],
      "close": 2798.0,
      "change": 36.5,
      "changePercent": 1.3217,
      "volume": 691700,
      "volumeRatio25": 1.3537,
      "distanceToMa25": 2.8692,
      "distanceToMa75": 7.0794,
      "distanceToMa200": 7.5995,
      "rci12": -19.58,
      "rci24": 61.22,
      "rci48": 81.82,
      "rangePosition52w": 100.0,
      "newHigh52w": true,
      "links": {
        "quote": "https://finance.yahoo.co.jp/quote/9001.T"
      }
    },
    {
      "rank": 38,
      "code": "9072",
      "name": "ニッコンホールディングス",
      "market": "プライム",
      "sector": "陸運業",
      "industry": "運輸・物流",
      "tags": [
        "tse",
        "prime",
        "陸運業",
        "運輸・物流"
      ],
      "close": 3730.0,
      "change": 35.0,
      "changePercent": 0.9472,
      "volume": 243400,
      "volumeRatio25": 0.9563,
      "distanceToMa25": 4.8259,
      "distanceToMa75": 6.3417,
      "distanceToMa200": 11.6078,
      "rci12": 72.03,
      "rci24": 92.89,
      "rci48": 26.11,
      "rangePosition52w": 100.0,
      "newHigh52w": true,
      "links": {
        "quote": "https://finance.yahoo.co.jp/quote/9072.T"
      }
    },
    {
      "rank": 39,
      "code": "6658",
      "name": "シライ電子工業",
      "market": "スタンダード",
      "sector": "電気機器",
      "industry": "電機・精密",
      "tags": [
        "tse",
        "standard",
        "電気機器",
        "電機・精密"
      ],
      "close": 771.0,
      "change": 6.0,
      "changePercent": 0.7843,
      "volume": 73900,
      "volumeRatio25": 0.826,
      "distanceToMa25": 4.8238,
      "distanceToMa75": 11.6938,
      "distanceToMa200": 23.5597,
      "rci12": 49.13,
      "rci24": 89.85,
      "rci48": 91.73,
      "rangePosition52w": 100.0,
      "newHigh52w": true,
      "links": {
        "quote": "https://finance.yahoo.co.jp/quote/6658.T"
      }
    },
    {
      "rank": 40,
      "code": "8045",
      "name": "横浜丸魚",
      "market": "スタンダード",
      "sector": "卸売業",
      "industry": "商社・卸売",
      "tags": [
        "tse",
        "standard",
        "卸売業",
        "商社・卸売"
      ],
      "close": 1630.0,
      "change": 9.0,
      "changePercent": 0.5552,
      "volume": 3200,
      "volumeRatio25": 1.6227,
      "distanceToMa25": 7.6448,
      "distanceToMa75": 26.3279,
      "distanceToMa200": 43.8487,
      "rci12": 5.24,
      "rci24": 82.54,
      "rci48": 93.53,
      "rangePosition52w": 100.0,
      "newHigh52w": true,
      "links": {
        "quote": "https://finance.yahoo.co.jp/quote/8045.T"
      }
    },
    {
      "rank": 41,
      "code": "5922",
      "name": "那須電機鉄工",
      "market": "スタンダード",
      "sector": "金属製品",
      "industry": "建設・資材",
      "tags": [
        "tse",
        "standard",
        "金属製品",
        "建設・資材"
      ],
      "close": 17800.0,
      "change": 90.0,
      "changePercent": 0.5082,
      "volume": 700,
      "volumeRatio25": 0.7991,
      "distanceToMa25": 1.9286,
      "distanceToMa75": 9.5762,
      "distanceToMa200": 21.8865,
      "rci12": 73.25,
      "rci24": 29.09,
      "rci48": 86.39,
      "rangePosition52w": 100.0,
      "newHigh52w": true,
      "links": {
        "quote": "https://finance.yahoo.co.jp/quote/5922.T"
      }
    },
    {
      "rank": 42,
      "code": "7487",
      "name": "小津産業",
      "market": "スタンダード",
      "sector": "卸売業",
      "industry": "商社・卸売",
      "tags": [
        "tse",
        "standard",
        "卸売業",
        "商社・卸売"
      ],
      "close": 1819.0,
      "change": 6.0,
      "changePercent": 0.3309,
      "volume": 8100,
      "volumeRatio25": 0.9392,
      "distanceToMa25": 1.4161,
      "distanceToMa75": 3.8384,
      "distanceToMa200": 6.0743,
      "rci12": 65.91,
      "rci24": 92.28,
      "rci48": 97.87,
      "rangePosition52w": 100.0,
      "newHigh52w": true,
      "links": {
        "quote": "https://finance.yahoo.co.jp/quote/7487.T"
      }
    },
    {
      "rank": 43,
      "code": "6734",
      "name": "ニューテック",
      "market": "スタンダード",
      "sector": "電気機器",
      "industry": "電機・精密",
      "tags": [
        "tse",
        "standard",
        "電気機器",
        "電機・精密"
      ],
      "close": 2649.0,
      "change": 2.0,
      "changePercent": 0.0756,
      "volume": 10000,
      "volumeRatio25": 0.9491,
      "distanceToMa25": 0.1679,
      "distanceToMa75": 24.5182,
      "distanceToMa200": 40.6794,
      "rci12": 85.84,
      "rci24": 96.2,
      "rci48": 92.86,
      "rangePosition52w": 100.0,
      "newHigh52w": true,
      "links": {
        "quote": "https://finance.yahoo.co.jp/quote/6734.T"
      }
    },
    {
      "rank": 44,
      "code": "5936",
      "name": "東洋シヤッター",
      "market": "スタンダード",
      "sector": "金属製品",
      "industry": "建設・資材",
      "tags": [
        "tse",
        "standard",
        "金属製品",
        "建設・資材"
      ],
      "close": 975.0,
      "change": 0.0,
      "changePercent": 0.0,
      "volume": 4500,
      "volumeRatio25": 0.5401,
      "distanceToMa25": 1.6811,
      "distanceToMa75": 5.3083,
      "distanceToMa200": 12.145,
      "rci12": 79.55,
      "rci24": 71.61,
      "rci48": 89.28,
      "rangePosition52w": 100.0,
      "newHigh52w": true,
      "links": {
        "quote": "https://finance.yahoo.co.jp/quote/5936.T"
      }
    }
  ]
}