{
  "date": "2026-02-12",
  "ranking": "新高値",
  "count": 50,
  "items": [
    {
      "rank": 1,
      "code": "4596",
      "name": "窪田製薬ホールディングス",
      "market": "グロース",
      "sector": "医薬品",
      "industry": "医薬品",
      "tags": [
        "tse",
        "growth",
        "医薬品"
      ],
      "close": 305.0,
      "change": 80.0,
      "changePercent": 35.5556,
      "volume": 14625100,
      "volumeRatio25": 1.2219,
      "distanceToMa25": 214.433,
      "distanceToMa75": 357.958,
      "distanceToMa200": 418.487,
      "rci12": 93.01,
      "rci24": 96.41,
      "rci48": 64.14,
      "rangePosition52w": 100.0,
      "newHigh52w": true,
      "links": {
        "quote": "https://finance.yahoo.co.jp/quote/4596.T"
      }
    },
    {
      "rank": 2,
      "code": "6072",
      "name": "地盤ネットホールディングス",
      "market": "スタンダード",
      "sector": "サービス業",
      "industry": "情報通信・サービスその他",
      "tags": [
        "tse",
        "standard",
        "サービス業",
        "情報通信・サービスその他"
      ],
      "close": 328.0,
      "change": 80.0,
      "changePercent": 32.2581,
      "volume": 146600,
      "volumeRatio25": 0.3979,
      "distanceToMa25": 56.399,
      "distanceToMa75": 76.4579,
      "distanceToMa200": 87.2413,
      "rci12": 72.38,
      "rci24": 24.59,
      "rci48": 86.46,
      "rangePosition52w": 100.0,
      "newHigh52w": true,
      "links": {
        "quote": "https://finance.yahoo.co.jp/quote/6072.T"
      }
    },
    {
      "rank": 3,
      "code": "3103",
      "name": "ユニチカ",
      "market": "プライム",
      "sector": "繊維製品",
      "industry": "素材・化学",
      "tags": [
        "tse",
        "prime",
        "繊維製品",
        "素材・化学"
      ],
      "close": 1372.0,
      "change": 300.0,
      "changePercent": 27.9851,
      "volume": 40208200,
      "volumeRatio25": 2.2963,
      "distanceToMa25": 150.5478,
      "distanceToMa75": 285.957,
      "distanceToMa200": 453.382,
      "rci12": 97.9,
      "rci24": 94.7,
      "rci48": 90.09,
      "rangePosition52w": 100.0,
      "newHigh52w": true,
      "links": {
        "quote": "https://finance.yahoo.co.jp/quote/3103.T"
      }
    },
    {
      "rank": 4,
      "code": "6862",
      "name": "ミナトホールディングス",
      "market": "スタンダード",
      "sector": "電気機器",
      "industry": "電機・精密",
      "tags": [
        "tse",
        "standard",
        "電気機器",
        "電機・精密"
      ],
      "close": 1922.0,
      "change": 400.0,
      "changePercent": 26.2812,
      "volume": 36700,
      "volumeRatio25": 0.145,
      "distanceToMa25": 17.9112,
      "distanceToMa75": 47.5148,
      "distanceToMa200": 91.8537,
      "rci12": -41.43,
      "rci24": -22.72,
      "rci48": 76.61,
      "rangePosition52w": 100.0,
      "newHigh52w": true,
      "links": {
        "quote": "https://finance.yahoo.co.jp/quote/6862.T"
      }
    },
    {
      "rank": 5,
      "code": "7794",
      "name": "イーディーピー",
      "market": "グロース",
      "sector": "その他製品",
      "industry": "情報通信・サービスその他",
      "tags": [
        "tse",
        "growth",
        "その他製品",
        "情報通信・サービスその他"
      ],
      "close": 1691.0,
      "change": 300.0,
      "changePercent": 21.5672,
      "volume": 1027300,
      "volumeRatio25": 0.5471,
      "distanceToMa25": 142.5973,
      "distanceToMa75": 221.9072,
      "distanceToMa200": 205.3752,
      "rci12": 86.01,
      "rci24": 90.61,
      "rci48": 87.84,
      "rangePosition52w": 100.0,
      "newHigh52w": true,
      "links": {
        "quote": "https://finance.yahoo.co.jp/quote/7794.T"
      }
    },
    {
      "rank": 6,
      "code": "4182",
      "name": "三菱瓦斯化学",
      "market": "プライム",
      "sector": "化学",
      "industry": "素材・化学",
      "tags": [
        "tse",
        "prime",
        "化学",
        "素材・化学"
      ],
      "close": 4124.0,
      "change": 700.0,
      "changePercent": 20.4439,
      "volume": 5313200,
      "volumeRatio25": 3.8536,
      "distanceToMa25": 30.5278,
      "distanceToMa75": 42.1389,
      "distanceToMa200": 57.6941,
      "rci12": 89.51,
      "rci24": 72.61,
      "rci48": 93.33,
      "rangePosition52w": 100.0,
      "newHigh52w": true,
      "links": {
        "quote": "https://finance.yahoo.co.jp/quote/4182.T"
      }
    },
    {
      "rank": 7,
      "code": "2962",
      "name": "テクニスコ",
      "market": "スタンダード",
      "sector": "金属製品",
      "industry": "建設・資材",
      "tags": [
        "tse",
        "standard",
        "金属製品",
        "建設・資材"
      ],
      "close": 888.0,
      "change": 150.0,
      "changePercent": 20.3252,
      "volume": 66400,
      "volumeRatio25": 0.1559,
      "distanceToMa25": 78.1416,
      "distanceToMa75": 106.8901,
      "distanceToMa200": 152.4664,
      "rci12": 86.01,
      "rci24": 43.5,
      "rci48": 82.76,
      "rangePosition52w": 100.0,
      "newHigh52w": true,
      "links": {
        "quote": "https://finance.yahoo.co.jp/quote/2962.T"
      }
    },
    {
      "rank": 8,
      "code": "5381",
      "name": "マイポックス",
      "market": "スタンダード",
      "sector": "ガラス・土石製品",
      "industry": "建設・資材",
      "tags": [
        "tse",
        "standard",
        "ガラス・土石製品",
        "建設・資材"
      ],
      "close": 921.0,
      "change": 150.0,
      "changePercent": 19.4553,
      "volume": 1859800,
      "volumeRatio25": 0.8367,
      "distanceToMa25": 60.9015,
      "distanceToMa75": 87.5815,
      "distanceToMa200": 88.4997,
      "rci12": 93.01,
      "rci24": 95.04,
      "rci48": 90.98,
      "rangePosition52w": 100.0,
      "newHigh52w": true,
      "links": {
        "quote": "https://finance.yahoo.co.jp/quote/5381.T"
      }
    },
    {
      "rank": 9,
      "code": "7771",
      "name": "日本精密",
      "market": "スタンダード",
      "sector": "精密機器",
      "industry": "電機・精密",
      "tags": [
        "tse",
        "standard",
        "精密機器",
        "電機・精密"
      ],
      "close": 925.0,
      "change": 150.0,
      "changePercent": 19.3548,
      "volume": 799900,
      "volumeRatio25": 0.1312,
      "distanceToMa25": 158.9586,
      "distanceToMa75": 417.2606,
      "distanceToMa200": 652.8282,
      "rci12": 99.3,
      "rci24": 82.89,
      "rci48": 93.49,
      "rangePosition52w": 100.0,
      "newHigh52w": true,
      "links": {
        "quote": "https://finance.yahoo.co.jp/quote/7771.T"
      }
    },
    {
      "rank": 10,
      "code": "5816",
      "name": "オーナンバ",
      "market": "スタンダード",
      "sector": "非鉄金属",
      "industry": "鉄鋼・非鉄",
      "tags": [
        "tse",
        "standard",
        "非鉄金属",
        "鉄鋼・非鉄"
      ],
      "close": 1778.0,
      "change": 278.0,
      "changePercent": 18.5333,
      "volume": 89100,
      "volumeRatio25": 6.3807,
      "distanceToMa25": 19.779,
      "distanceToMa75": 23.104,
      "distanceToMa200": 51.3185,
      "rci12": 87.41,
      "rci24": 8.5,
      "rci48": 9.25,
      "rangePosition52w": 100.0,
      "newHigh52w": true,
      "links": {
        "quote": "https://finance.yahoo.co.jp/quote/5816.T"
      }
    },
    {
      "rank": 11,
      "code": "1514",
      "name": "住石ホールディングス",
      "market": "スタンダード",
      "sector": "鉱業",
      "industry": "エネルギー資源",
      "tags": [
        "tse",
        "standard",
        "鉱業",
        "エネルギー資源"
      ],
      "close": 962.0,
      "change": 150.0,
      "changePercent": 18.4729,
      "volume": 2488800,
      "volumeRatio25": 1.2426,
      "distanceToMa25": 39.2669,
      "distanceToMa75": 60.5546,
      "distanceToMa200": 53.9828,
      "rci12": 52.27,
      "rci24": 85.98,
      "rci48": 85.61,
      "rangePosition52w": 100.0,
      "newHigh52w": true,
      "links": {
        "quote": "https://finance.yahoo.co.jp/quote/1514.T"
      }
    },
    {
      "rank": 12,
      "code": "6326",
      "name": "クボタ",
      "market": "プライム",
      "sector": "機械",
      "industry": "機械",
      "tags": [
        "tse",
        "prime",
        "機械"
      ],
      "close": 3242.0,
      "change": 500.0,
      "changePercent": 18.2349,
      "volume": 15085800,
      "volumeRatio25": 3.173,
      "distanceToMa25": 31.2062,
      "distanceToMa75": 42.8202,
      "distanceToMa200": 68.2967,
      "rci12": 94.41,
      "rci24": 46.96,
      "rci48": 76.0,
      "rangePosition52w": 100.0,
      "newHigh52w": true,
      "links": {
        "quote": "https://finance.yahoo.co.jp/quote/6326.T"
      }
    },
    {
      "rank": 13,
      "code": "5016",
      "name": "ＪＸ金属",
      "market": "プライム",
      "sector": "非鉄金属",
      "industry": "鉄鋼・非鉄",
      "tags": [
        "tse",
        "prime",
        "非鉄金属",
        "鉄鋼・非鉄"
      ],
      "close": 3280.0,
      "change": 500.5,
      "changePercent": 18.0068,
      "volume": 17930200,
      "volumeRatio25": 0.5025,
      "distanceToMa25": 28.6325,
      "distanceToMa75": 58.4495,
      "distanceToMa200": 121.7907,
      "rci12": 45.45,
      "rci24": 42.0,
      "rci48": 90.38,
      "rangePosition52w": 100.0,
      "newHigh52w": true,
      "links": {
        "quote": "https://finance.yahoo.co.jp/quote/5016.T"
      }
    },
    {
      "rank": 14,
      "code": "6627",
      "name": "テラプローブ",
      "market": "スタンダード",
      "sector": "電気機器",
      "industry": "電機・精密",
      "tags": [
        "tse",
        "standard",
        "電気機器",
        "電機・精密"
      ],
      "close": 9900.0,
      "change": 1500.0,
      "changePercent": 17.8571,
      "volume": 36900,
      "volumeRatio25": 0.4508,
      "distanceToMa25": 35.8845,
      "distanceToMa75": 56.2993,
      "distanceToMa200": 111.4237,
      "rci12": 26.57,
      "rci24": 75.76,
      "rci48": 91.44,
      "rangePosition52w": 100.0,
      "newHigh52w": true,
      "links": {
        "quote": "https://finance.yahoo.co.jp/quote/6627.T"
      }
    },
    {
      "rank": 15,
      "code": "8050",
      "name": "セイコーグループ",
      "market": "プライム",
      "sector": "精密機器",
      "industry": "電機・精密",
      "tags": [
        "tse",
        "prime",
        "精密機器",
        "電機・精密"
      ],
      "close": 10060.0,
      "change": 1500.0,
      "changePercent": 17.5234,
      "volume": 59500,
      "volumeRatio25": 0.5379,
      "distanceToMa25": 30.6697,
      "distanceToMa75": 36.5067,
      "distanceToMa200": 70.9838,
      "rci12": 94.41,
      "rci24": 75.04,
      "rci48": 58.93,
      "rangePosition52w": 100.0,
      "newHigh52w": true,
      "links": {
        "quote": "https://finance.yahoo.co.jp/quote/8050.T"
      }
    },
    {
      "rank": 16,
      "code": "6085",
      "name": "アーキテクツ・スタジオ・ジャパン",
      "market": "グロース",
      "sector": "サービス業",
      "industry": "情報通信・サービスその他",
      "tags": [
        "tse",
        "growth",
        "サービス業",
        "情報通信・サービスその他"
      ],
      "close": 1015.0,
      "change": 150.0,
      "changePercent": 17.341,
      "volume": 551000,
      "volumeRatio25": 2.0243,
      "distanceToMa25": 110.8434,
      "distanceToMa75": 174.5123,
      "distanceToMa200": 242.0445,
      "rci12": 96.5,
      "rci24": 83.37,
      "rci48": 70.13,
      "rangePosition52w": 100.0,
      "newHigh52w": true,
      "links": {
        "quote": "https://finance.yahoo.co.jp/quote/6085.T"
      }
    },
    {
      "rank": 17,
      "code": "5741",
      "name": "ＵＡＣＪ",
      "market": "プライム",
      "sector": "非鉄金属",
      "industry": "鉄鋼・非鉄",
      "tags": [
        "tse",
        "prime",
        "非鉄金属",
        "鉄鋼・非鉄"
      ],
      "close": 3390.0,
      "change": 500.0,
      "changePercent": 17.301,
      "volume": 1647000,
      "volumeRatio25": 1.9205,
      "distanceToMa25": 37.8811,
      "distanceToMa75": 57.832,
      "distanceToMa200": 101.535,
      "rci12": 87.94,
      "rci24": 96.76,
      "rci48": 97.87,
      "rangePosition52w": 100.0,
      "newHigh52w": true,
      "links": {
        "quote": "https://finance.yahoo.co.jp/quote/5741.T"
      }
    },
    {
      "rank": 18,
      "code": "7800",
      "name": "アミファ",
      "market": "スタンダード",
      "sector": "その他製品",
      "industry": "情報通信・サービスその他",
      "tags": [
        "tse",
        "standard",
        "その他製品",
        "情報通信・サービスその他"
      ],
      "close": 1018.0,
      "change": 150.0,
      "changePercent": 17.2811,
      "volume": 43600,
      "volumeRatio25": 2.6592,
      "distanceToMa25": 44.005,
      "distanceToMa75": 55.3218,
      "distanceToMa200": 58.9259,
      "rci12": 80.94,
      "rci24": 90.3,
      "rci48": 90.33,
      "rangePosition52w": 100.0,
      "newHigh52w": true,
      "links": {
        "quote": "https://finance.yahoo.co.jp/quote/7800.T"
      }
    },
    {
      "rank": 19,
      "code": "6440",
      "name": "ＪＵＫＩ",
      "market": "プライム",
      "sector": "機械",
      "industry": "機械",
      "tags": [
        "tse",
        "prime",
        "機械"
      ],
      "close": 680.0,
      "change": 100.0,
      "changePercent": 17.2414,
      "volume": 1654900,
      "volumeRatio25": 6.4511,
      "distanceToMa25": 26.8941,
      "distanceToMa75": 39.726,
      "distanceToMa200": 57.6793,
      "rci12": 86.01,
      "rci24": 71.85,
      "rci48": 94.99,
      "rangePosition52w": 100.0,
      "newHigh52w": true,
      "links": {
        "quote": "https://finance.yahoo.co.jp/quote/6440.T"
      }
    },
    {
      "rank": 20,
      "code": "6728",
      "name": "アルバック",
      "market": "プライム",
      "sector": "電気機器",
      "industry": "電機・精密",
      "tags": [
        "tse",
        "prime",
        "電気機器",
        "電機・精密"
      ],
      "close": 10320.0,
      "change": 1503.0,
      "changePercent": 17.0466,
      "volume": 275700,
      "volumeRatio25": 0.7178,
      "distanceToMa25": 24.7727,
      "distanceToMa75": 41.0681,
      "distanceToMa200": 65.1976,
      "rci12": 65.56,
      "rci24": 75.89,
      "rci48": 92.93,
      "rangePosition52w": 100.0,
      "newHigh52w": true,
      "links": {
        "quote": "https://finance.yahoo.co.jp/quote/6728.T"
      }
    },
    {
      "rank": 21,
      "code": "6134",
      "name": "ＦＵＪＩ",
      "market": "プライム",
      "sector": "機械",
      "industry": "機械",
      "tags": [
        "tse",
        "prime",
        "機械"
      ],
      "close": 4863.0,
      "change": 700.0,
      "changePercent": 16.8148,
      "volume": 197600,
      "volumeRatio25": 0.5856,
      "distanceToMa25": 23.3437,
      "distanceToMa75": 38.1327,
      "distanceToMa200": 66.2931,
      "rci12": 51.05,
      "rci24": 23.98,
      "rci48": 87.89,
      "rangePosition52w": 100.0,
      "newHigh52w": true,
      "links": {
        "quote": "https://finance.yahoo.co.jp/quote/6134.T"
      }
    },
    {
      "rank": 22,
      "code": "4620",
      "name": "藤倉化成",
      "market": "スタンダード",
      "sector": "化学",
      "industry": "素材・化学",
      "tags": [
        "tse",
        "standard",
        "化学",
        "素材・化学"
      ],
      "close": 1060.0,
      "change": 150.0,
      "changePercent": 16.4835,
      "volume": 489500,
      "volumeRatio25": 1.8042,
      "distanceToMa25": 46.9121,
      "distanceToMa75": 62.5401,
      "distanceToMa200": 80.8349,
      "rci12": 92.31,
      "rci24": 86.54,
      "rci48": 84.63,
      "rangePosition52w": 100.0,
      "newHigh52w": true,
      "links": {
        "quote": "https://finance.yahoo.co.jp/quote/4620.T"
      }
    },
    {
      "rank": 23,
      "code": "3288",
      "name": "オープンハウスグループ",
      "market": "プライム",
      "sector": "不動産業",
      "industry": "不動産",
      "tags": [
        "tse",
        "prime",
        "不動産業",
        "不動産"
      ],
      "close": 11045.0,
      "change": 1500.0,
      "changePercent": 15.715,
      "volume": 1188900,
      "volumeRatio25": 4.3313,
      "distanceToMa25": 18.0814,
      "distanceToMa75": 25.1499,
      "distanceToMa200": 45.4591,
      "rci12": 77.62,
      "rci24": -31.39,
      "rci48": 53.44,
      "rangePosition52w": 100.0,
      "newHigh52w": true,
      "links": {
        "quote": "https://finance.yahoo.co.jp/quote/3288.T"
      }
    },
    {
      "rank": 24,
      "code": "2344",
      "name": "平安レイサービス",
      "market": "スタンダード",
      "sector": "サービス業",
      "industry": "情報通信・サービスその他",
      "tags": [
        "tse",
        "standard",
        "サービス業",
        "情報通信・サービスその他"
      ],
      "close": 1122.0,
      "change": 150.0,
      "changePercent": 15.4321,
      "volume": 14400,
      "volumeRatio25": 0.9732,
      "distanceToMa25": 17.6101,
      "distanceToMa75": 19.9641,
      "distanceToMa200": 20.5305,
      "rci12": 97.2,
      "rci24": 27.91,
      "rci48": 80.12,
      "rangePosition52w": 100.0,
      "newHigh52w": true,
      "links": {
        "quote": "https://finance.yahoo.co.jp/quote/2344.T"
      }
    },
    {
      "rank": 25,
      "code": "5956",
      "name": "トーソー",
      "market": "スタンダード",
      "sector": "金属製品",
      "industry": "建設・資材",
      "tags": [
        "tse",
        "standard",
        "金属製品",
        "建設・資材"
      ],
      "close": 762.0,
      "change": 100.0,
      "changePercent": 15.1057,
      "volume": 57900,
      "volumeRatio25": 5.3295,
      "distanceToMa25": 19.1817,
      "distanceToMa75": 29.5918,
      "distanceToMa200": 36.9555,
      "rci12": 37.06,
      "rci24": 43.85,
      "rci48": 88.66,
      "rangePosition52w": 100.0,
      "newHigh52w": true,
      "links": {
        "quote": "https://finance.yahoo.co.jp/quote/5956.T"
      }
    },
    {
      "rank": 26,
      "code": "9385",
      "name": "ショーエイコーポレーション",
      "market": "スタンダード",
      "sector": "化学",
      "industry": "素材・化学",
      "tags": [
        "tse",
        "standard",
        "化学",
        "素材・化学"
      ],
      "close": 788.0,
      "change": 100.0,
      "changePercent": 14.5349,
      "volume": 40800,
      "volumeRatio25": 2.65,
      "distanceToMa25": 18.9829,
      "distanceToMa75": 27.1077,
      "distanceToMa200": 36.0274,
      "rci12": 97.03,
      "rci24": 84.22,
      "rci48": 92.61,
      "rangePosition52w": 100.0,
      "newHigh52w": true,
      "links": {
        "quote": "https://finance.yahoo.co.jp/quote/9385.T"
      }
    },
    {
      "rank": 27,
      "code": "4247",
      "name": "ポバール興業",
      "market": "スタンダード",
      "sector": "化学",
      "industry": "素材・化学",
      "tags": [
        "tse",
        "standard",
        "化学",
        "素材・化学"
      ],
      "close": 1620.0,
      "change": 188.0,
      "changePercent": 13.1285,
      "volume": 10000,
      "volumeRatio25": 7.9114,
      "distanceToMa25": 18.0827,
      "distanceToMa75": 23.2689,
      "distanceToMa200": 30.1848,
      "rci12": 97.2,
      "rci24": 71.28,
      "rci48": 90.51,
      "rangePosition52w": 100.0,
      "newHigh52w": true,
      "links": {
        "quote": "https://finance.yahoo.co.jp/quote/4247.T"
      }
    },
    {
      "rank": 28,
      "code": "9361",
      "name": "伏木海陸運送",
      "market": "スタンダード",
      "sector": "倉庫・運輸関連業",
      "industry": "運輸・物流",
      "tags": [
        "tse",
        "standard",
        "倉庫・運輸関連業",
        "運輸・物流"
      ],
      "close": 2490.0,
      "change": 268.0,
      "changePercent": 12.0612,
      "volume": 5400,
      "volumeRatio25": 4.5918,
      "distanceToMa25": 16.1792,
      "distanceToMa75": 28.3849,
      "distanceToMa200": 40.3529,
      "rci12": 87.94,
      "rci24": 14.5,
      "rci48": 73.52,
      "rangePosition52w": 100.0,
      "newHigh52w": true,
      "links": {
        "quote": "https://finance.yahoo.co.jp/quote/9361.T"
      }
    },
    {
      "rank": 29,
      "code": "5367",
      "name": "ニッカトー",
      "market": "スタンダード",
      "sector": "ガラス・土石製品",
      "industry": "建設・資材",
      "tags": [
        "tse",
        "standard",
        "ガラス・土石製品",
        "建設・資材"
      ],
      "close": 778.0,
      "change": 73.0,
      "changePercent": 10.3546,
      "volume": 198200,
      "volumeRatio25": 4.358,
      "distanceToMa25": 17.2746,
      "distanceToMa75": 26.2031,
      "distanceToMa200": 37.9054,
      "rci12": 62.06,
      "rci24": 63.96,
      "rci48": 89.31,
      "rangePosition52w": 100.0,
      "newHigh52w": true,
      "links": {
        "quote": "https://finance.yahoo.co.jp/quote/5367.T"
      }
    },
    {
      "rank": 30,
      "code": "7777",
      "name": "スリー・ディー・マトリックス",
      "market": "グロース",
      "sector": "精密機器",
      "industry": "電機・精密",
      "tags": [
        "tse",
        "growth",
        "精密機器",
        "電機・精密"
      ],
      "close": 549.0,
      "change": 43.0,
      "changePercent": 8.498,
      "volume": 8376800,
      "volumeRatio25": 1.1969,
      "distanceToMa25": 24.3094,
      "distanceToMa75": 49.3742,
      "distanceToMa200": 103.2468,
      "rci12": 86.71,
      "rci24": 56.87,
      "rci48": 86.43,
      "rangePosition52w": 100.0,
      "newHigh52w": true,
      "links": {
        "quote": "https://finance.yahoo.co.jp/quote/7777.T"
      }
    },
    {
      "rank": 31,
      "code": "8393",
      "name": "宮崎銀行",
      "market": "プライム",
      "sector": "銀行業",
      "industry": "銀行",
      "tags": [
        "tse",
        "prime",
        "銀行業",
        "銀行"
      ],
      "close": 9640.0,
      "change": 690.0,
      "changePercent": 7.7095,
      "volume": 143500,
      "volumeRatio25": 1.5855,
      "distanceToMa25": 22.4407,
      "distanceToMa75": 52.5799,
      "distanceToMa200": 100.798,
      "rci12": 89.34,
      "rci24": 95.15,
      "rci48": 98.71,
      "rangePosition52w": 100.0,
      "newHigh52w": true,
      "links": {
        "quote": "https://finance.yahoo.co.jp/quote/8393.T"
      }
    },
    {
      "rank": 32,
      "code": "4970",
      "name": "東洋合成工業",
      "market": "スタンダード",
      "sector": "化学",
      "industry": "素材・化学",
      "tags": [
        "tse",
        "standard",
        "化学",
        "素材・化学"
      ],
      "close": 10480.0,
      "change": 750.0,
      "changePercent": 7.7081,
      "volume": 107100,
      "volumeRatio25": 1.4725,
      "distanceToMa25": 25.2689,
      "distanceToMa75": 43.5695,
      "distanceToMa200": 75.1966,
      "rci12": 46.68,
      "rci24": 90.57,
      "rci48": 92.93,
      "rangePosition52w": 100.0,
      "newHigh52w": true,
      "links": {
        "quote": "https://finance.yahoo.co.jp/quote/4970.T"
      }
    },
    {
      "rank": 33,
      "code": "1994",
      "name": "高橋カーテンウォール工業",
      "market": "スタンダード",
      "sector": "建設業",
      "industry": "建設・資材",
      "tags": [
        "tse",
        "standard",
        "建設業",
        "建設・資材"
      ],
      "close": 590.0,
      "change": 40.0,
      "changePercent": 7.2727,
      "volume": 21700,
      "volumeRatio25": 1.7857,
      "distanceToMa25": 8.5277,
      "distanceToMa75": 12.7906,
      "distanceToMa200": 16.9637,
      "rci12": 60.84,
      "rci24": 20.2,
      "rci48": 84.9,
      "rangePosition52w": 100.0,
      "newHigh52w": true,
      "links": {
        "quote": "https://finance.yahoo.co.jp/quote/1994.T"
      }
    },
    {
      "rank": 34,
      "code": "5939",
      "name": "大谷工業",
      "market": "スタンダード",
      "sector": "金属製品",
      "industry": "建設・資材",
      "tags": [
        "tse",
        "standard",
        "金属製品",
        "建設・資材"
      ],
      "close": 8490.0,
      "change": 540.0,
      "changePercent": 6.7925,
      "volume": 11000,
      "volumeRatio25": 2.5,
      "distanceToMa25": 21.3342,
      "distanceToMa75": 44.6469,
      "distanceToMa200": 51.3355,
      "rci12": 97.2,
      "rci24": 92.48,
      "rci48": 97.19,
      "rangePosition52w": 100.0,
      "newHigh52w": true,
      "links": {
        "quote": "https://finance.yahoo.co.jp/quote/5939.T"
      }
    },
    {
      "rank": 35,
      "code": "1944",
      "name": "きんでん",
      "market": "プライム",
      "sector": "建設業",
      "industry": "建設・資材",
      "tags": [
        "tse",
        "prime",
        "建設業",
        "建設・資材"
      ],
      "close": 8357.0,
      "change": 456.0,
      "changePercent": 5.7714,
      "volume": 1086300,
      "volumeRatio25": 1.3975,
      "distanceToMa25": 12.8867,
      "distanceToMa75": 24.2625,
      "distanceToMa200": 55.7322,
      "rci12": 41.96,
      "rci24": 12.87,
      "rci48": 77.59,
      "rangePosition52w": 100.0,
      "newHigh52w": true,
      "links": {
        "quote": "https://finance.yahoo.co.jp/quote/1944.T"
      }
    },
    {
      "rank": 36,
      "code": "4732",
      "name": "ユー・エス・エス",
      "market": "プライム",
      "sector": "サービス業",
      "industry": "情報通信・サービスその他",
      "tags": [
        "tse",
        "prime",
        "サービス業",
        "情報通信・サービスその他"
      ],
      "close": 1858.0,
      "change": 100.0,
      "changePercent": 5.6883,
      "volume": 3106600,
      "volumeRatio25": 3.0381,
      "distanceToMa25": 6.9562,
      "distanceToMa75": 7.696,
      "distanceToMa200": 11.09,
      "rci12": 78.32,
      "rci24": -27.57,
      "rci48": 18.15,
      "rangePosition52w": 100.0,
      "newHigh52w": true,
      "links": {
        "quote": "https://finance.yahoo.co.jp/quote/4732.T"
      }
    },
    {
      "rank": 37,
      "code": "8541",
      "name": "愛媛銀行",
      "market": "プライム",
      "sector": "銀行業",
      "industry": "銀行",
      "tags": [
        "tse",
        "prime",
        "銀行業",
        "銀行"
      ],
      "close": 2020.0,
      "change": 107.0,
      "changePercent": 5.5933,
      "volume": 155800,
      "volumeRatio25": 1.2327,
      "distanceToMa25": 17.9355,
      "distanceToMa75": 38.4017,
      "distanceToMa200": 64.3298,
      "rci12": 92.31,
      "rci24": 91.72,
      "rci48": 98.27,
      "rangePosition52w": 100.0,
      "newHigh52w": true,
      "links": {
        "quote": "https://finance.yahoo.co.jp/quote/8541.T"
      }
    },
    {
      "rank": 38,
      "code": "3465",
      "name": "ケイアイスター不動産",
      "market": "プライム",
      "sector": "不動産業",
      "industry": "不動産",
      "tags": [
        "tse",
        "prime",
        "不動産業",
        "不動産"
      ],
      "close": 7000.0,
      "change": 360.0,
      "changePercent": 5.4217,
      "volume": 170300,
      "volumeRatio25": 4.08,
      "distanceToMa25": 7.7918,
      "distanceToMa75": 14.857,
      "distanceToMa200": 28.365,
      "rci12": 87.41,
      "rci24": -39.13,
      "rci48": 38.49,
      "rangePosition52w": 100.0,
      "newHigh52w": true,
      "links": {
        "quote": "https://finance.yahoo.co.jp/quote/3465.T"
      }
    },
    {
      "rank": 39,
      "code": "9532",
      "name": "大阪瓦斯",
      "market": "プライム",
      "sector": "電気・ガス業",
      "industry": "電力・ガス",
      "tags": [
        "tse",
        "prime",
        "電気・ガス業",
        "電力・ガス"
      ],
      "close": 6737.0,
      "change": 341.0,
      "changePercent": 5.3315,
      "volume": 1420600,
      "volumeRatio25": 1.4114,
      "distanceToMa25": 15.1742,
      "distanceToMa75": 25.58,
      "distanceToMa200": 51.2865,
      "rci12": 97.9,
      "rci24": 98.52,
      "rci48": 92.53,
      "rangePosition52w": 100.0,
      "newHigh52w": true,
      "links": {
        "quote": "https://finance.yahoo.co.jp/quote/9532.T"
      }
    },
    {
      "rank": 40,
      "code": "5018",
      "name": "ＭＯＲＥＳＣＯ",
      "market": "スタンダード",
      "sector": "石油・石炭製品",
      "industry": "エネルギー資源",
      "tags": [
        "tse",
        "standard",
        "石油・石炭製品",
        "エネルギー資源"
      ],
      "close": 2050.0,
      "change": 101.0,
      "changePercent": 5.1821,
      "volume": 97300,
      "volumeRatio25": 1.2637,
      "distanceToMa25": 12.0488,
      "distanceToMa75": 32.6838,
      "distanceToMa200": 49.3157,
      "rci12": 76.22,
      "rci24": 76.37,
      "rci48": 96.43,
      "rangePosition52w": 100.0,
      "newHigh52w": true,
      "links": {
        "quote": "https://finance.yahoo.co.jp/quote/5018.T"
      }
    },
    {
      "rank": 41,
      "code": "7608",
      "name": "エスケイジャパン",
      "market": "スタンダード",
      "sector": "卸売業",
      "industry": "商社・卸売",
      "tags": [
        "tse",
        "standard",
        "卸売業",
        "商社・卸売"
      ],
      "close": 831.5,
      "change": 39.0,
      "changePercent": 4.9211,
      "volume": 256600,
      "volumeRatio25": 1.2334,
      "distanceToMa25": 8.1865,
      "distanceToMa75": 14.9285,
      "distanceToMa200": 39.4263,
      "rci12": 49.65,
      "rci24": -7.83,
      "rci48": 69.06,
      "rangePosition52w": 100.0,
      "newHigh52w": true,
      "links": {
        "quote": "https://finance.yahoo.co.jp/quote/7608.T"
      }
    },
    {
      "rank": 42,
      "code": "5922",
      "name": "那須電機鉄工",
      "market": "スタンダード",
      "sector": "金属製品",
      "industry": "建設・資材",
      "tags": [
        "tse",
        "standard",
        "金属製品",
        "建設・資材"
      ],
      "close": 20300.0,
      "change": 940.0,
      "changePercent": 4.8554,
      "volume": 10900,
      "volumeRatio25": 7.3649,
      "distanceToMa25": 13.9374,
      "distanceToMa75": 23.3063,
      "distanceToMa200": 37.5558,
      "rci12": 87.41,
      "rci24": 47.2,
      "rci48": 90.3,
      "rangePosition52w": 100.0,
      "newHigh52w": true,
      "links": {
        "quote": "https://finance.yahoo.co.jp/quote/5922.T"
      }
    },
    {
      "rank": 43,
      "code": "3513",
      "name": "イチカワ",
      "market": "スタンダード",
      "sector": "繊維製品",
      "industry": "素材・化学",
      "tags": [
        "tse",
        "standard",
        "繊維製品",
        "素材・化学"
      ],
      "close": 3680.0,
      "change": 170.0,
      "changePercent": 4.8433,
      "volume": 22000,
      "volumeRatio25": 1.3067,
      "distanceToMa25": 8.9583,
      "distanceToMa75": 37.9138,
      "distanceToMa200": 71.6282,
      "rci12": -5.77,
      "rci24": 61.65,
      "rci48": 94.78,
      "rangePosition52w": 100.0,
      "newHigh52w": true,
      "links": {
        "quote": "https://finance.yahoo.co.jp/quote/3513.T"
      }
    },
    {
      "rank": 44,
      "code": "4631",
      "name": "ＤＩＣ",
      "market": "プライム",
      "sector": "化学",
      "industry": "素材・化学",
      "tags": [
        "tse",
        "prime",
        "化学",
        "素材・化学"
      ],
      "close": 4368.0,
      "change": 199.0,
      "changePercent": 4.7733,
      "volume": 1041300,
      "volumeRatio25": 1.4674,
      "distanceToMa25": 14.7939,
      "distanceToMa75": 16.2246,
      "distanceToMa200": 29.6502,
      "rci12": 93.01,
      "rci24": 80.59,
      "rci48": 25.17,
      "rangePosition52w": 100.0,
      "newHigh52w": true,
      "links": {
        "quote": "https://finance.yahoo.co.jp/quote/4631.T"
      }
    },
    {
      "rank": 45,
      "code": "8078",
      "name": "阪和興業",
      "market": "プライム",
      "sector": "卸売業",
      "industry": "商社・卸売",
      "tags": [
        "tse",
        "prime",
        "卸売業",
        "商社・卸売"
      ],
      "close": 8850.0,
      "change": 390.0,
      "changePercent": 4.6099,
      "volume": 201700,
      "volumeRatio25": 1.8163,
      "distanceToMa25": 11.3544,
      "distanceToMa75": 22.719,
      "distanceToMa200": 40.1275,
      "rci12": 88.81,
      "rci24": 65.67,
      "rci48": 93.41,
      "rangePosition52w": 100.0,
      "newHigh52w": true,
      "links": {
        "quote": "https://finance.yahoo.co.jp/quote/8078.T"
      }
    },
    {
      "rank": 46,
      "code": "5071",
      "name": "ヴィス",
      "market": "スタンダード",
      "sector": "サービス業",
      "industry": "情報通信・サービスその他",
      "tags": [
        "tse",
        "standard",
        "サービス業",
        "情報通信・サービスその他"
      ],
      "close": 1620.0,
      "change": 71.0,
      "changePercent": 4.5836,
      "volume": 31100,
      "volumeRatio25": 4.9491,
      "distanceToMa25": 8.5645,
      "distanceToMa75": 14.7374,
      "distanceToMa200": 20.8576,
      "rci12": 90.21,
      "rci24": 20.78,
      "rci48": 81.94,
      "rangePosition52w": 100.0,
      "newHigh52w": true,
      "links": {
        "quote": "https://finance.yahoo.co.jp/quote/5071.T"
      }
    },
    {
      "rank": 47,
      "code": "8343",
      "name": "秋田銀行",
      "market": "プライム",
      "sector": "銀行業",
      "industry": "銀行",
      "tags": [
        "tse",
        "prime",
        "銀行業",
        "銀行"
      ],
      "close": 5730.0,
      "change": 250.0,
      "changePercent": 4.562,
      "volume": 112900,
      "volumeRatio25": 0.9662,
      "distanceToMa25": 18.4864,
      "distanceToMa75": 37.8796,
      "distanceToMa200": 62.4564,
      "rci12": 98.6,
      "rci24": 93.07,
      "rci48": 95.52,
      "rangePosition52w": 100.0,
      "newHigh52w": true,
      "links": {
        "quote": "https://finance.yahoo.co.jp/quote/8343.T"
      }
    },
    {
      "rank": 48,
      "code": "5384",
      "name": "フジミインコーポレーテッド",
      "market": "プライム",
      "sector": "ガラス・土石製品",
      "industry": "建設・資材",
      "tags": [
        "tse",
        "prime",
        "ガラス・土石製品",
        "建設・資材"
      ],
      "close": 3120.0,
      "change": 136.0,
      "changePercent": 4.5576,
      "volume": 579800,
      "volumeRatio25": 1.3255,
      "distanceToMa25": 14.4954,
      "distanceToMa75": 25.7875,
      "distanceToMa200": 40.994,
      "rci12": 83.74,
      "rci24": 93.54,
      "rci48": 86.2,
      "rangePosition52w": 100.0,
      "newHigh52w": true,
      "links": {
        "quote": "https://finance.yahoo.co.jp/quote/5384.T"
      }
    },
    {
      "rank": 49,
      "code": "6273",
      "name": "ＳＭＣ",
      "market": "プライム",
      "sector": "機械",
      "industry": "機械",
      "tags": [
        "tse",
        "prime",
        "機械"
      ],
      "close": 71740.0,
      "change": 3120.0,
      "changePercent": 4.5468,
      "volume": 591400,
      "volumeRatio25": 1.7304,
      "distanceToMa25": 13.4818,
      "distanceToMa75": 25.2564,
      "distanceToMa200": 36.9955,
      "rci12": 86.71,
      "rci24": 41.72,
      "rci48": 76.8,
      "rangePosition52w": 100.0,
      "newHigh52w": true,
      "links": {
        "quote": "https://finance.yahoo.co.jp/quote/6273.T"
      }
    },
    {
      "rank": 50,
      "code": "6647",
      "name": "森尾電機",
      "market": "スタンダード",
      "sector": "電気機器",
      "industry": "電機・精密",
      "tags": [
        "tse",
        "standard",
        "電気機器",
        "電機・精密"
      ],
      "close": 2749.0,
      "change": 119.0,
      "changePercent": 4.5247,
      "volume": 3900,
      "volumeRatio25": 2.0228,
      "distanceToMa25": 15.5061,
      "distanceToMa75": 20.1801,
      "distanceToMa200": 38.0162,
      "rci12": 47.55,
      "rci24": 51.74,
      "rci48": 64.52,
      "rangePosition52w": 100.0,
      "newHigh52w": true,
      "links": {
        "quote": "https://finance.yahoo.co.jp/quote/6647.T"
      }
    }
  ]
}